gtfs_station_stop/__init__.py
gtfs_station_stop/__main__.py
gtfs_station_stop/alert.py
gtfs_station_stop/arrival.py
gtfs_station_stop/calendar.py
gtfs_station_stop/const.py
gtfs_station_stop/feed_subject.py
gtfs_station_stop/helpers.py
gtfs_station_stop/route_info.py
gtfs_station_stop/route_status.py
gtfs_station_stop/schedule.py
gtfs_station_stop/static_dataset.py
gtfs_station_stop/station_stop.py
gtfs_station_stop/station_stop_info.py
gtfs_station_stop/stop_times.py
gtfs_station_stop/trip_info.py
gtfs_station_stop/updatable.py
gtfs_station_stop-0.11.5.dist-info/METADATA
gtfs_station_stop-0.11.5.dist-info/WHEEL
gtfs_station_stop-0.11.5.dist-info/licenses/LICENSE
gtfs_station_stop-0.11.5.dist-info/RECORD
