Metadata-Version: 2.4
Name: gtfs_station_stop
Version: 0.11.5
Summary: Package for reading and organizing GTFS data for a given station stop.
Project-URL: Homepage, https://github.com/bcpearce/gtfs-station-stop
Project-URL: Issues, https://github.com/bcpearce/gtfs-station-stop/issues
Author-email: Benjamin Pearce <gtfs@bcpearce.com>
License-File: LICENSE
Classifier: License :: OSI Approved :: MIT License
Classifier: Operating System :: OS Independent
Classifier: Programming Language :: Python :: 3
Requires-Python: >=3.13.2
Requires-Dist: aiofiles>=24.1.0
Requires-Dist: aiohttp>=3.11.11
Requires-Dist: asyncio-atexit>=1.0.1
Requires-Dist: coverage-badge>=1.1.2
Requires-Dist: gtfs-realtime-bindings>=2.0.0
Requires-Dist: protobuf!=6.31.0
Requires-Dist: requests>=2.32.3
